<?xml version="1.0" encoding="UTF-8" ?>
<!DOCTYPE mapper PUBLIC "-//mybatis.org//DTD Mapper 3.0//EN" "http://mybatis.org/dtd/mybatis-3-mapper.dtd" >
<mapper namespace="net.fnsco.order.service.dao.master.trade.TradeByHourDao" >
  <resultMap id="BaseResultMap" type="net.fnsco.order.service.domain.trade.TradeByHour" >
    <result column="id" property="id" jdbcType="INTEGER" />
    <result column="trade_hour" property="tradeHour" jdbcType="VARCHAR" />
    <result column="trade_date" property="tradeDate" jdbcType="VARCHAR" />
    <result column="inner_code" property="innerCode" jdbcType="VARCHAR" />
    <result column="turnover" property="turnover" jdbcType="DECIMAL" />
    <result column="order_num" property="orderNum" jdbcType="INTEGER" />
    <result column="order_price" property="orderPrice" jdbcType="DECIMAL" />
  </resultMap>
  <sql id="Base_Column_List" >
    id, trade_hour, trade_date, inner_code, turnover, order_num, order_price
  </sql>
  <insert id="insert" parameterType="net.fnsco.order.service.domain.trade.TradeByHour" >
    insert into r_trade_by_hour (id, trade_hour, trade_date, 
      inner_code, turnover, order_num, 
      order_price)
    values (#{id,jdbcType=INTEGER}, #{tradeHour,jdbcType=VARCHAR}, #{tradeDate,jdbcType=VARCHAR}, 
      #{innerCode,jdbcType=VARCHAR}, #{turnover,jdbcType=DECIMAL}, #{orderNum,jdbcType=INTEGER}, 
      #{orderPrice,jdbcType=DECIMAL})
  </insert>
  <insert id="insertSelective" parameterType="net.fnsco.order.service.domain.trade.TradeByHour" >
    insert into r_trade_by_hour
    <trim prefix="(" suffix=")" suffixOverrides="," >
      <if test="id != null" >
        id,
      </if>
      <if test="tradeHour != null" >
        trade_hour,
      </if>
      <if test="tradeDate != null" >
        trade_date,
      </if>
      <if test="innerCode != null" >
        inner_code,
      </if>
      <if test="turnover != null" >
        turnover,
      </if>
      <if test="orderNum != null" >
        order_num,
      </if>
      <if test="orderPrice != null" >
        order_price,
      </if>
    </trim>
    <trim prefix="values (" suffix=")" suffixOverrides="," >
      <if test="id != null" >
        #{id,jdbcType=INTEGER},
      </if>
      <if test="tradeHour != null" >
        #{tradeHour,jdbcType=VARCHAR},
      </if>
      <if test="tradeDate != null" >
        #{tradeDate,jdbcType=VARCHAR},
      </if>
      <if test="innerCode != null" >
        #{innerCode,jdbcType=VARCHAR},
      </if>
      <if test="turnover != null" >
        #{turnover,jdbcType=DECIMAL},
      </if>
      <if test="orderNum != null" >
        #{orderNum,jdbcType=INTEGER},
      </if>
      <if test="orderPrice != null" >
        #{orderPrice,jdbcType=DECIMAL},
      </if>
    </trim>
  </insert>
  <!-- 根据条件查询 -->
  <select id="selectByCondition" parameterType="net.fnsco.order.service.domain.trade.TradeByHour" resultType="net.fnsco.order.api.dto.TradeHourDTO">
     SELECT
			trade_hour AS tradeHour,
			SUM(turnover) AS turnover,
			SUM(order_num) AS orderNum
		FROM
			r_trade_by_hour
		<where>
		      <if test="startTradeDate != null and  startTradeDate != ''">
		        AND trade_date &gt;= #{startTradeDate}
		      </if>
		       <if test="endTradeDate != null and  endTradeDate != ''">
		        AND trade_date &lt;= #{endTradeDate}
		      </if>
		      <if test="tradeDate != null and  tradeDate != ''">
		        AND trade_date= #{tradeDate}
		      </if>
		      <if test="userId != null">
		       AND inner_code in (
		         SELECT inner_code FROM u_app_user_merchant WHERE app_user_id=#{userId}
		         <if test="roleId != null">
		           AND role_id = #{roleId}
		         </if>
		       )
		      </if>
		      <if test="innerCode != null and innerCode != ''">
		      AND inner_code = #{innerCode}
		      </if>
		</where>	
		GROUP BY trade_hour
  </select>
  <!-- 根据条件删除 -->
  <delete id="deleteByCondition" parameterType="net.fnsco.order.service.domain.trade.TradeByHour">
    DELETE FROM r_trade_by_hour 
    <where>
      <if test="startTradeDate != null">
         AND trade_date &gt;= #{startTradeDate}
       </if>
       <if test="endTradeDate != null and  endTradeDate != ''">
        AND trade_date &lt;  #{endTradeDate}
      </if>
      <if test="tradeDate != null and  tradeDate != ''">
        AND trade_date= #{tradeDate}
      </if>
    </where>
  </delete>
  <!-- 批量插入数据 -->
  <insert id="insertBatch" parameterType="java.util.List">
  	 <selectKey resultType ="java.lang.Integer" keyProperty= "id" order= "AFTER">
                 SELECT LAST_INSERT_ID()
     </selectKey >
     insert into r_trade_by_hour (id, trade_hour, trade_date, 
      inner_code, turnover, order_num, 
      order_price)
    values
     <foreach collection ="list" item="hourTrade" index= "index" separator =",">
      (#{hourTrade.id,jdbcType=INTEGER}, #{hourTrade.tradeHour,jdbcType=VARCHAR}, #{hourTrade.tradeDate,jdbcType=VARCHAR}, 
      #{hourTrade.innerCode,jdbcType=VARCHAR}, #{hourTrade.turnover,jdbcType=DECIMAL}, #{hourTrade.orderNum,jdbcType=INTEGER}, 
      #{hourTrade.orderPrice,jdbcType=DECIMAL})
     </foreach>
  </insert>
</mapper>